{"meta":{"name":"The Blacklist","id":"notmesmeric170","type":"channel","posterShape":"landscape","videos":[{"id":"notmesmericstream_170_0","title":"The Blacklist S01 E01"},{"id":"notmesmericstream_170_1","title":"The Blacklist S01 E02"},{"id":"notmesmericstream_170_2","title":"The Blacklist S01 E03"},{"id":"notmesmericstream_170_3","title":"The Blacklist S01 E04"},{"id":"notmesmericstream_170_4","title":"The Blacklist S01 E05"},{"id":"notmesmericstream_170_5","title":"The Blacklist S01 E06"},{"id":"notmesmericstream_170_6","title":"The Blacklist S01 E07"},{"id":"notmesmericstream_170_7","title":"The Blacklist S01 E08"},{"id":"notmesmericstream_170_8","title":"The Blacklist S01 E09"},{"id":"notmesmericstream_170_9","title":"The Blacklist S01 E10"},{"id":"notmesmericstream_170_10","title":"The Blacklist S01 E11"},{"id":"notmesmericstream_170_11","title":"The Blacklist S01 E12"},{"id":"notmesmericstream_170_12","title":"The Blacklist S01 E13"},{"id":"notmesmericstream_170_13","title":"The Blacklist S01 E14"},{"id":"notmesmericstream_170_14","title":"The Blacklist S01 E15"},{"id":"notmesmericstream_170_15","title":"The Blacklist S01 E16"},{"id":"notmesmericstream_170_16","title":"The Blacklist S01 E17"},{"id":"notmesmericstream_170_17","title":"The Blacklist S01 E18"},{"id":"notmesmericstream_170_18","title":"The Blacklist S01 E19"},{"id":"notmesmericstream_170_19","title":"The Blacklist S01 E20"},{"id":"notmesmericstream_170_20","title":"The Blacklist S01 E21"},{"id":"notmesmericstream_170_21","title":"The Blacklist S01 E22"},{"id":"notmesmericstream_170_22","title":"The Blacklist S02 E01"},{"id":"notmesmericstream_170_23","title":"The Blacklist S02 E02"},{"id":"notmesmericstream_170_24","title":"The Blacklist S02 E03"},{"id":"notmesmericstream_170_25","title":"The Blacklist S02 E04"},{"id":"notmesmericstream_170_26","title":"The Blacklist S02 E05"},{"id":"notmesmericstream_170_27","title":"The Blacklist S02 E06"},{"id":"notmesmericstream_170_28","title":"The Blacklist S02 E07"},{"id":"notmesmericstream_170_29","title":"The Blacklist S02 E08"},{"id":"notmesmericstream_170_30","title":"The Blacklist S02 E09"},{"id":"notmesmericstream_170_31","title":"The Blacklist S02 E10"},{"id":"notmesmericstream_170_32","title":"The Blacklist S02 E11"},{"id":"notmesmericstream_170_33","title":"The Blacklist S02 E12"},{"id":"notmesmericstream_170_34","title":"The Blacklist S02 E13"},{"id":"notmesmericstream_170_35","title":"The Blacklist S02 E14"},{"id":"notmesmericstream_170_36","title":"The Blacklist S02 E15"},{"id":"notmesmericstream_170_37","title":"The Blacklist S02 E16"},{"id":"notmesmericstream_170_38","title":"The Blacklist S02 E17"},{"id":"notmesmericstream_170_39","title":"The Blacklist S02 E18"},{"id":"notmesmericstream_170_40","title":"The Blacklist S02 E19"},{"id":"notmesmericstream_170_41","title":"The Blacklist S02 E20"},{"id":"notmesmericstream_170_42","title":"The Blacklist S02 E21"},{"id":"notmesmericstream_170_43","title":"The Blacklist S02 E22"},{"id":"notmesmericstream_170_44","title":"The Blacklist S03 E01"},{"id":"notmesmericstream_170_45","title":"The Blacklist S03 E02"},{"id":"notmesmericstream_170_46","title":"The Blacklist S03 E03"},{"id":"notmesmericstream_170_47","title":"The Blacklist S03 E04"},{"id":"notmesmericstream_170_48","title":"The Blacklist S03 E05"},{"id":"notmesmericstream_170_49","title":"The Blacklist S03 E06"},{"id":"notmesmericstream_170_50","title":"The Blacklist S03 E07"},{"id":"notmesmericstream_170_51","title":"The Blacklist S03 E08"},{"id":"notmesmericstream_170_52","title":"The Blacklist S03 E09"},{"id":"notmesmericstream_170_53","title":"The Blacklist S03 E10"},{"id":"notmesmericstream_170_54","title":"The Blacklist S03 E11"},{"id":"notmesmericstream_170_55","title":"The Blacklist S03 E12"},{"id":"notmesmericstream_170_56","title":"The Blacklist S03 E13"},{"id":"notmesmericstream_170_57","title":"The Blacklist S03 E14"},{"id":"notmesmericstream_170_58","title":"The Blacklist S03 E15"},{"id":"notmesmericstream_170_59","title":"The Blacklist S03 E16"},{"id":"notmesmericstream_170_60","title":"The Blacklist S03 E17"},{"id":"notmesmericstream_170_61","title":"The Blacklist S03 E18"},{"id":"notmesmericstream_170_62","title":"The Blacklist S03 E19"},{"id":"notmesmericstream_170_63","title":"The Blacklist S03 E20"},{"id":"notmesmericstream_170_64","title":"The Blacklist S03 E21"},{"id":"notmesmericstream_170_65","title":"The Blacklist S03 E22"},{"id":"notmesmericstream_170_66","title":"The Blacklist S03 E23"},{"id":"notmesmericstream_170_67","title":"The Blacklist S04 E01"},{"id":"notmesmericstream_170_68","title":"The Blacklist S04 E02"},{"id":"notmesmericstream_170_69","title":"The Blacklist S04 E03"},{"id":"notmesmericstream_170_70","title":"The Blacklist S04 E04"},{"id":"notmesmericstream_170_71","title":"The Blacklist S04 E05"},{"id":"notmesmericstream_170_72","title":"The Blacklist S04 E06"},{"id":"notmesmericstream_170_73","title":"The Blacklist S04 E07"},{"id":"notmesmericstream_170_74","title":"The Blacklist S04 E08"},{"id":"notmesmericstream_170_75","title":"The Blacklist S04 E09"},{"id":"notmesmericstream_170_76","title":"The Blacklist S04 E10"},{"id":"notmesmericstream_170_77","title":"The Blacklist S04 E11"},{"id":"notmesmericstream_170_78","title":"The Blacklist S04 E12"},{"id":"notmesmericstream_170_79","title":"The Blacklist S04 E13"},{"id":"notmesmericstream_170_80","title":"The Blacklist S04 E14"},{"id":"notmesmericstream_170_81","title":"The Blacklist S04 E15"},{"id":"notmesmericstream_170_82","title":"The Blacklist S04 E16"},{"id":"notmesmericstream_170_83","title":"The Blacklist S04 E17"},{"id":"notmesmericstream_170_84","title":"The Blacklist S04 E18"},{"id":"notmesmericstream_170_85","title":"The Blacklist S04 E19"},{"id":"notmesmericstream_170_86","title":"The Blacklist S04 E20"},{"id":"notmesmericstream_170_87","title":"The Blacklist S04 E21"},{"id":"notmesmericstream_170_88","title":"The Blacklist S04 E22"},{"id":"notmesmericstream_170_89","title":"The Blacklist S05 E01"},{"id":"notmesmericstream_170_90","title":"The Blacklist S05 E02"},{"id":"notmesmericstream_170_91","title":"The Blacklist S05 E03"},{"id":"notmesmericstream_170_92","title":"The Blacklist S05 E04"},{"id":"notmesmericstream_170_93","title":"The Blacklist S05 E05"},{"id":"notmesmericstream_170_94","title":"The Blacklist S05 E06"},{"id":"notmesmericstream_170_95","title":"The Blacklist S05 E07"},{"id":"notmesmericstream_170_96","title":"The Blacklist S05 E08"},{"id":"notmesmericstream_170_97","title":"The Blacklist S05 E09"},{"id":"notmesmericstream_170_98","title":"The Blacklist S05 E10"},{"id":"notmesmericstream_170_99","title":"The Blacklist S05 E11"},{"id":"notmesmericstream_170_100","title":"The Blacklist S05 E12"},{"id":"notmesmericstream_170_101","title":"The Blacklist S05 E13"},{"id":"notmesmericstream_170_102","title":"The Blacklist S05 E14"},{"id":"notmesmericstream_170_103","title":"The Blacklist S05 E15"},{"id":"notmesmericstream_170_104","title":"The Blacklist S05 E16"},{"id":"notmesmericstream_170_105","title":"The Blacklist S05 E17"},{"id":"notmesmericstream_170_106","title":"The Blacklist S05 E18"},{"id":"notmesmericstream_170_107","title":"The Blacklist S05 E19"},{"id":"notmesmericstream_170_108","title":"The Blacklist S05 E20"},{"id":"notmesmericstream_170_109","title":"The Blacklist S05 E21"},{"id":"notmesmericstream_170_110","title":"The Blacklist S05 E22"},{"id":"notmesmericstream_170_111","title":"The Blacklist S06 E01"},{"id":"notmesmericstream_170_112","title":"The Blacklist S06 E02"},{"id":"notmesmericstream_170_113","title":"The Blacklist S06 E03"},{"id":"notmesmericstream_170_114","title":"The Blacklist S06 E04"},{"id":"notmesmericstream_170_115","title":"The Blacklist S06 E05"},{"id":"notmesmericstream_170_116","title":"The Blacklist S06 E06"},{"id":"notmesmericstream_170_117","title":"The Blacklist S06 E07"},{"id":"notmesmericstream_170_118","title":"The Blacklist S06 E08"},{"id":"notmesmericstream_170_119","title":"The Blacklist S06 E09"},{"id":"notmesmericstream_170_120","title":"The Blacklist S06 E10"},{"id":"notmesmericstream_170_121","title":"The Blacklist S06 E11"},{"id":"notmesmericstream_170_122","title":"The Blacklist S06 E12"},{"id":"notmesmericstream_170_123","title":"The Blacklist S06 E13"},{"id":"notmesmericstream_170_124","title":"The Blacklist S06 E14"},{"id":"notmesmericstream_170_125","title":"The Blacklist S06 E15"},{"id":"notmesmericstream_170_126","title":"The Blacklist S06 E16"},{"id":"notmesmericstream_170_127","title":"The Blacklist S06 E17"},{"id":"notmesmericstream_170_128","title":"The Blacklist S06 E18"},{"id":"notmesmericstream_170_129","title":"The Blacklist S06 E19"},{"id":"notmesmericstream_170_130","title":"The Blacklist S06 E20"},{"id":"notmesmericstream_170_131","title":"The Blacklist S06 E21"},{"id":"notmesmericstream_170_132","title":"The Blacklist S06 E22"},{"id":"notmesmericstream_170_133","title":"The Blacklist S07 E01"},{"id":"notmesmericstream_170_134","title":"The Blacklist S07 E02"},{"id":"notmesmericstream_170_135","title":"The Blacklist S07 E03"},{"id":"notmesmericstream_170_136","title":"The Blacklist S07 E04"},{"id":"notmesmericstream_170_137","title":"The Blacklist S07 E05"},{"id":"notmesmericstream_170_138","title":"The Blacklist S07 E06"},{"id":"notmesmericstream_170_139","title":"The Blacklist S07 E07"},{"id":"notmesmericstream_170_140","title":"The Blacklist S07 E08"},{"id":"notmesmericstream_170_141","title":"The Blacklist S07 E09"},{"id":"notmesmericstream_170_142","title":"The Blacklist S07 E10"},{"id":"notmesmericstream_170_143","title":"The Blacklist S07 E11"},{"id":"notmesmericstream_170_144","title":"The Blacklist S07 E12"},{"id":"notmesmericstream_170_145","title":"The Blacklist S07 E13"},{"id":"notmesmericstream_170_146","title":"The Blacklist S07 E14"},{"id":"notmesmericstream_170_147","title":"The Blacklist S07 E15"},{"id":"notmesmericstream_170_148","title":"The Blacklist S07 E16"},{"id":"notmesmericstream_170_149","title":"The Blacklist S07 E17"},{"id":"notmesmericstream_170_150","title":"The Blacklist S07 E18"},{"id":"notmesmericstream_170_151","title":"The Blacklist S07 E19"}]}}